ezfiles/__init__.py
ezfiles/files.py
ezfiles-0.0.1.dist-info/METADATA
ezfiles-0.0.1.dist-info/WHEEL
ezfiles-0.0.1.dist-info/top_level.txt
ezfiles-0.0.1.dist-info/RECORD
